field_manager_api/__init__.py
field_manager_api/auth/__init__.py
field_manager_api/auth/auth.py
field_manager_api/config/__init__.py
field_manager_api/config/config.py
field_manager_api/config/request_handler.py
field_manager_api/export/__init__.py
field_manager_api/export/export_data.py
field_manager_api/field_manager.py
field_manager_api/locations/__init__.py
field_manager_api/locations/get_locations.py
field_manager_api/locations/models.py
field_manager_api/methods/__init__.py
field_manager_api/methods/get_methods.py
field_manager_api/methods/models.py
field_manager_api/nadag/nadag_api.py
field_manager_api/plot/__init__.py
field_manager_api/plot/plot_methods.py
field_manager_api/projects/__init__.py
field_manager_api/projects/get_projects.py
field_manager_api/utils/__init__.py
field_manager_api/utils/automatic_datarapport.py
field_manager_api/utils/folium_plotter.py
field_manager_api/utils/ground_models.py
field_manager_api-0.0.2.dist-info/LICENSE
field_manager_api-0.0.2.dist-info/METADATA
field_manager_api-0.0.2.dist-info/WHEEL
field_manager_api-0.0.2.dist-info/RECORD
