Metadata-Version: 2.1
Name: field-manager-api
Version: 0.0.2
Summary: Field Manager API SDK
Home-page: https://github.com/norwegian-geotechnical-institute/field-manager-api
License: MIT
Author: Jostein Leira
Author-email: 9363084+josteinl@users.noreply.github.com
Requires-Python: >3.10,<4.0
Classifier: Development Status :: 3 - Alpha
Classifier: License :: OSI Approved :: MIT License
Classifier: Operating System :: OS Independent
Classifier: Programming Language :: Python :: 3
Classifier: Programming Language :: Python :: 3.11
Classifier: Programming Language :: Python :: 3.12
Classifier: Topic :: Scientific/Engineering :: GIS
Requires-Dist: folium (>=0.17.0,<0.18.0)
Requires-Dist: jupyter (>=1.1.1,<2.0.0)
Requires-Dist: matplotlib (>=3.9.2,<4.0.0)
Requires-Dist: nbformat (>=5.10.4,<6.0.0)
Requires-Dist: pandas (>=2.2.3,<3.0.0)
Requires-Dist: plotly (>=5.24.1,<6.0.0)
Requires-Dist: pyproj (>=3.6.1,<4.0.0)
Requires-Dist: python-docx (>=1.1.2,<2.0.0)
Requires-Dist: scipy (>=1.14.1,<2.0.0)
Requires-Dist: selenium (>=4.24.0,<5.0.0)
Requires-Dist: shapely (>=2.0.6,<3.0.0)
Requires-Dist: webdriver-manager (>=4.0.2,<5.0.0)
Project-URL: Repository, https://github.com/norwegian-geotechnical-institute/field-manager-api
